gadfastcron/__init__.py
gadfastcron/setup.py
gadfastcron/const/__init__.py
gadfastcron/const/symbols.py
gadfastcron/jobstores/__init__.py
gadfastcron/jobstores/memory.py
gadfastcron/jobstores/mongo.py
gadfastcron/jobstores/redis.py
gadfastcron/jobstores/sqlalchemy.py
gadfastcron/triggers/__init__.py
gadfastcron/triggers/cron.py
gadfastcron/triggers/date.py
gadfastcron-0.0.1.dist-info/LICENSE
gadfastcron-0.0.1.dist-info/METADATA
gadfastcron-0.0.1.dist-info/WHEEL
gadfastcron-0.0.1.dist-info/top_level.txt
gadfastcron-0.0.1.dist-info/RECORD
