Metadata-Version: 2.1
Name: gadfastcron
Version: 0.0.1
Summary: Wrapper around APScheduler for managing scheduled tasks.
Home-page: https://github.com/AlexDemure/gadfastcron
Author: Alexander Grishchenko
Author-email: alexanderdemure@gmail.com
Classifier: Programming Language :: Python :: 3
Classifier: License :: OSI Approved :: MIT License
Classifier: Operating System :: OS Independent
Requires-Python: >=3.8
License-File: LICENSE
Requires-Dist: apscheduler
